{
  "alerts": {},
  "config_snapshot": {
    "dates": [
      "2026-07-20",
      "2026-07-21",
      "2026-07-22",
      "2026-07-23",
      "2026-07-24",
      "2026-07-25"
    ],
    "destinations": [
      "IST",
      "SAW"
    ],
    "min_valid_price_try": 500.0,
    "origins": [
      "AMS",
      "EIN",
      "RTM"
    ],
    "recipient": "zubeyirtemel@outlook.com",
    "sender": "talhabozan@gmail.com",
    "threshold_try": 10000.0,
    "trip_type": "one-way"
  },
  "consecutive_failures": 0,
  "current_cheap_flights": [
    {
      "airline": "?",
      "arrival": "?",
      "currency": "USD",
      "date": "2026-07-23",
      "departure": "?",
      "dest": "IST",
      "duration": "?",
      "origin": "AMS",
      "price_str": "$212",
      "price_try": 9628.56,
      "stops": "Unknown"
    },
    {
      "airline": "LOT",
      "arrival": "1:05 PM on Sat, Jul 25",
      "currency": "USD",
      "date": "2026-07-24",
      "departure": "2:15 PM on Fri, Jul 24",
      "dest": "IST",
      "duration": "21 hr 50 min",
      "origin": "AMS",
      "price_str": "$212",
      "price_try": 9628.56,
      "stops": 1
    },
    {
      "airline": "Air Serbia",
      "arrival": "3:55 PM on Sat, Jul 25",
      "currency": "USD",
      "date": "2026-07-24",
      "departure": "9:10 PM on Fri, Jul 24",
      "dest": "IST",
      "duration": "17 hr 45 min",
      "origin": "AMS",
      "price_str": "$213",
      "price_try": 9673.98,
      "stops": 1
    }
  ],
  "last_run": "2026-05-13T17:54:34.062113+00:00",
  "latest_error": {
    "message": "send_alert failed: (535, b'5.7.8 Username and Password not accepted. For more information, go to\\n5.7.8  https://support.google.com/mail/?p=BadCredentials a92af1059eb24-134cbcb9ed3sm220487c88.1 - gsmtp')",
    "timestamp": "2026-05-13T17:54:34.061737+00:00"
  },
  "recent_runs": [
    {
      "cheap_count": 3,
      "cheapest_try": 9628.56,
      "dry_run": false,
      "duration_sec": 76.2,
      "emails_sent": 0,
      "new_alert_count": 2,
      "queries_failed": 2,
      "smtp_msg": "SMTP authentication FAILED: 535 b'5.7.8 Username and Password not accepted. For more information, go to\\n5.7.8  https://support.google.com/mail/?p=BadCredentials a92af1059eb24-134cc33aac9sm112468c88.14 - gsmtp'. Common causes: (1) sender email mismatch — the app password belongs to talhabozan@gmail.com; (2) 2-Step Verification disabled on the Google account; (3) wrong/old app password in the GMAIL_APP_PASSWORD secret.",
      "smtp_ok": false,
      "timestamp": "2026-05-13T17:54:34.062093+00:00",
      "total_flights": 879,
      "total_queries": 36
    }
  ],
  "stats": {
    "total_emails_sent": 0,
    "total_runs": 1
  }
}